pyuu/common/__init__.py
pyuu/env/__init__.py
pyuu/icl/__init__.py
pyuu/icl/inf.py
pyuu/icl/itv.py
pyuu/icl/itvset_rbtree.py
pyuu/icl/itvset_treap.py
pyuu/iter/__init__.py
pyuu/iter/bfs.py
pyuu/iter/common.py
pyuu/iter/dfs.py
pyuu/iter/tree_iter.py
pyuu/path/__init__.py
pyuu/path/common.py
pyuu/path/path.py
pyuu/path/vpath.py
pyuu/project/__init__.py
pyuu/seq/__init__.py
pyuu/shell/__init__.py
pyuu/signed_set/__init__.py
pyuu/signed_set/signed_set.py
pyuu/trivial/__init__.py
pyuu/uimport/__init__.py
pyuu.uimport-0.0.0.dist-info/METADATA
pyuu.uimport-0.0.0.dist-info/WHEEL
pyuu.uimport-0.0.0.dist-info/top_level.txt
pyuu.uimport-0.0.0.dist-info/RECORD
