Metadata-Version: 2.1
Name: pyuu.uimport
Version: 0.0.0
Summary: import utils
Home-page: https://github.com/happyxianyu/uu
Author: happyxianyu
Author-email: happyxianyu623@outlook.com
License: Apache License 2.0
Requires-Python: >=3.8
Requires-Dist: pyuu.path
